Metadata-Version: 2.1
Name: agmonsynchrony
Version: 0.1.0
Summary: Synchrony index between time series based on Agmon's paper
Home-page: http://github.com/jacquemv/agmonsynchrony
Author: Vincent Jacquemet
Author-email: vincent.jacquemet@umontreal.ca
License: MIT
Keywords: time series,synchrony,neuron,spikes
License-File: LICENSE
